odoo10_addon_partner_contact_personal_information_page-10.0.1.0.0-py2.7-nspkg.pth
odoo/addons/partner_contact_personal_information_page/__manifest__.py
odoo/addons/partner_contact_personal_information_page/__init__.py
odoo/addons/partner_contact_personal_information_page/README.rst
odoo/addons/partner_contact_personal_information_page/i18n/es.po
odoo/addons/partner_contact_personal_information_page/i18n/sl.po
odoo/addons/partner_contact_personal_information_page/i18n/nl.po
odoo/addons/partner_contact_personal_information_page/i18n/de.po
odoo/addons/partner_contact_personal_information_page/i18n/fr.po
odoo/addons/partner_contact_personal_information_page/i18n/partner_contact_personal_information_page.pot
odoo/addons/partner_contact_personal_information_page/views/res_partner.xml
odoo/addons/partner_contact_personal_information_page/static/description/icon.png
odoo10_addon_partner_contact_personal_information_page-10.0.1.0.0.dist-info/top_level.txt
odoo10_addon_partner_contact_personal_information_page-10.0.1.0.0.dist-info/WHEEL
odoo10_addon_partner_contact_personal_information_page-10.0.1.0.0.dist-info/RECORD
odoo10_addon_partner_contact_personal_information_page-10.0.1.0.0.dist-info/metadata.json
odoo10_addon_partner_contact_personal_information_page-10.0.1.0.0.dist-info/DESCRIPTION.rst
odoo10_addon_partner_contact_personal_information_page-10.0.1.0.0.dist-info/METADATA
odoo10_addon_partner_contact_personal_information_page-10.0.1.0.0.dist-info/namespace_packages.txt
