Metadata-Version: 2.0
Name: odoo10-addon-partner-contact-personal-information-page
Version: 10.0.1.0.0
Summary: Add a page to contacts form to put personal information
Home-page: https://odoo-community.org/
Author: UNKNOWN
Author-email: UNKNOWN
License: AGPL-3
Platform: UNKNOWN
Requires-Dist: odoo (<10.1dev,>=10.0)
Classifier: Programming Language :: Python :: 2.7
Classifier: Framework :: Odoo
Classifier: License :: OSI Approved :: GNU Affero General Public License v3
